{
  "Овсяная мука": 367,
  "Овсянка": 389,
  "Гречка": 343,
  "Нут": 364,
  "Чечевица": 352,
  "Киноа": 368,
  "Кус-кус": 376,
  "Пшено": 348,
  "Рис": 130,
  "Рис бурый": 123,
  "Красная рыба": 206,
  "Тунец консервированный в с/с": 116,
  "Семга слабосоленая": 269,
  "Креветки": 99,
  "Кальмар": 92,
  "Гребешок": 111,
  "Крабовое мясо": 84,
  "Горбуша": 142,
  "Треска": 82,
  "Минтай": 72,
  "Говядина": 250,
  "Свинина": 242,
  "Курица": 239,
  "Индейка": 189,
  "Бедро индейки": 179,
  "Бедро курицы": 209,
  "Помидоры": 18,
  "Огурцы": 15,
  "Баклажан": 25,
  "Кабачок": 17,
  "Морковь": 41,
  "Лук": 40,
  "Авокадо": 160,
  "Капуста белокочанная": 25,
  "Капуста пекинская": 16,
  "Капуста цветная": 25,
  "Брокколи": 34,
  "Сельдерей": 16,
  "Перец болгарский": 20,
  "Картошка": 77,
  "Помидоры черри": 18,
  "Редис": 16,
  "Горошек консервы": 79,
  "Горошек свежий": 81,
  "Стручковая фасоль": 31,
  "Свекла": 43,
  "Оливковое масло": 884,
  "Масло Гхи": 900,
  "Сливочное масло 82%": 717,
  "Грецкий орех": 654,
  "Фундук": 628,
  "Кедровый орех": 673,
  "Кешью": 553,
  "Миндаль": 579,
  "Тыквенные семечки": 559,
  "Семечки подсолнечника": 584,
  "Сыр твердый 35%": 356,
  "Сыр творожный": 342,
  "Сыр моцарелла": 280,
  "Сыр обезжиренный 10-20%": 250,
  "Творог 5%": 145,
  "Творог обезжиренный": 71,
  "Молоко 2,5%": 50,
  "Рикотта": 174,
  "Йогурт натуральный": 61,
  "Кефир 3,2%": 60,
  "Кефир 2,5%": 50,
  "Йогурт греческий 2%": 59,
  "Сыр фетакса": 265,
  "Сметана 10%": 115,
  "Сметана 20%": 206,
  "Сметана 15%": 162,
  "Сливки 10%": 118,
  "Сыр Тильзитер": 345,
  "Ряженка 2,5%": 54,
  "Голубика": 57,
  "Клубника": 32,
  "Малина": 52,
  "Вишня": 50,
  "Арбуз": 30,
  "Яблоко": 52,
  "Банан": 89,
  "Груша": 57,
  "Апельсин": 47,
  "Ананас консервы": 60,
  "Ананас": 50,
  "Лимон": 29,
  "Киви": 61,
  "Гранат": 83,
  "Черешня": 63,
  "Хурма": 70,
  "Мандарины": 53,
  "Хлебцы рисовые": 384,
  "Яйца": 155,
  "Арахисовая паста": 588,
  "Маслины": 115,
  "Шампиньоны": 22,
  "Кокосовая стружка": 660,
  "Мед": 304,
  "Протеин 30гр": 120,
  "Сироп агавы": 310,
  "Кунжут": 573,
  "Семена льна": 534,
  "Чиа": 486,
  "Пшеничные отруби": 216,
  "Какао порошок": 228,
  "Хлеб": 265,
  "Чеснок": 149,
  "Лимонный сок": 22,
  "Тортилья": 270,
  "Лаваш": 290,
  "Томатная паста": 82,
  "Фасоль консервы": 82,
  "Кукуруза консервы": 58,
  "Желатин": 355,
  "Соевый соус": 53,
  "Горчица": 66,
  "Соба": 99,
  "Макароны": 371,
  "Морковь по-корейски": 150,
  "Квашенная капуста": 19,
  "Шпинат": 23,
  "Айсберг": 14,
  "Петрушка": 36,
  "Укроп": 43,
  "Финики": 282,
  "Изюм": 299,
  "Курага": 241
}
